{
  "id": "bespeco_62_slpj600",
  "name": "Bespeco SLPJ600",
  "brand": "bespeco",
  "category": "general",
  "description": "Bespeco SLPJ600",
  "media": {
    "thumbnail": "/data/thumbnails/bespeco_62_slpj600.jpg",
    "gallery": [],
    "videos": []
  },
  "commercial": {
    "price": 60.0,
    "link": "https://www.halilit.com/items/3363759-bespeco-slpj600",
    "status": "IN_STOCK"
  },
  "specs": {},
  "badges": [
    "HALILIT_CERTIFIED"
  ],
  "meta": {
    "completeness": "SKELETON",
    "last_scan": "2026-01-24T02:39:32.899131Z"
  }
}