{
  "id": "marimba_one_1036154_marimba_one_one_vibe_silver_no_motor",
  "name": "Marimba One One Vibe Silver no motor",
  "brand": "marimba-one",
  "category": "general",
  "description": "Marimba One One Vibe Silver no motor",
  "media": {
    "thumbnail": "https://d3m9l0v76dty0.cloudfront.net/system/photos/1534284/original/02d951d58c08c0b8822f5a56680d08ac.jpg",
    "gallery": [],
    "videos": []
  },
  "commercial": {
    "price": 0.0,
    "link": "https://www.halilit.com/items/1036154-marimba-one-one-vibe-silver-no-motor",
    "status": "IN_STOCK"
  },
  "specs": {},
  "badges": [
    "HALILIT_CERTIFIED"
  ],
  "meta": {
    "completeness": "SKELETON",
    "last_scan": "2026-01-24T04:11:22.145515Z"
  }
}