{
  "id": "m_audio_52_oxygen25mkv",
  "name": "M-Audio Oxygen 25 MKV",
  "brand": "m-audio",
  "category": "studio",
  "description": "M-Audio Oxygen 25 MKV",
  "media": {
    "thumbnail": "https://d3m9l0v76dty0.cloudfront.net/system/photos/8782063/original/a513db05ebf0e1e7b15b04a2fbe39753.jpg",
    "gallery": [],
    "videos": []
  },
  "commercial": {
    "price": 500.0,
    "link": "https://www.halilit.com/items/4633097-m-audio-oxygen-25-mkv",
    "status": "IN_STOCK"
  },
  "specs": {},
  "badges": [
    "HALILIT_CERTIFIED"
  ],
  "meta": {
    "completeness": "SKELETON",
    "last_scan": "2026-01-24T04:10:19.983672Z"
  }
}