{
  "brand_identity": {
    "id": "perri-s-leathers",
    "name": "PERRI-S-LEATHERS"
  },
  "products": [
    {
      "id": "perri_s_leathers_57_8168",
      "name": "Perri's Leathers LPCP-8168",
      "brand": "perri-s-leathers",
      "category": "general",
      "image_url": "/data/thumbnails/perri_s_leathers_57_8168.jpg",
      "description": "Perri's Leathers LPCP-8168"
    },
    {
      "id": "perri_s_leathers_57_7552",
      "name": "Perri's Leathers VGS-7552",
      "brand": "perri-s-leathers",
      "category": "general",
      "image_url": "/data/thumbnails/perri_s_leathers_57_7552.jpg",
      "description": "Perri's Leathers VGS-7552"
    },
    {
      "id": "perri_s_leathers_57_7112",
      "name": "Perri's Leathers P25STUD-7112",
      "brand": "perri-s-leathers",
      "category": "general",
      "image_url": "/data/thumbnails/perri_s_leathers_57_7112.jpg",
      "description": "Perri's Leathers P25STUD-7112"
    },
    {
      "id": "perri_s_leathers_57_7581",
      "name": "Perri's Leathers TWS-7581",
      "brand": "perri-s-leathers",
      "category": "general",
      "image_url": "/data/thumbnails/perri_s_leathers_57_7581.jpg",
      "description": "Perri's Leathers TWS-7581"
    },
    {
      "id": "perri_s_leathers_57_8170",
      "name": "Perri's Leathers UKNWSP-8170",
      "brand": "perri-s-leathers",
      "category": "general",
      "image_url": "/data/thumbnails/perri_s_leathers_57_8170.jpg",
      "description": "Perri's Leathers UKNWSP-8170"
    },
    {
      "id": "perri_s_leathers_57_8177",
      "name": "Perri's Leathers LPCP-8177",
      "brand": "perri-s-leathers",
      "category": "general",
      "image_url": "/data/thumbnails/perri_s_leathers_57_8177.jpg",
      "description": "Perri's Leathers LPCP-8177"
    },
    {
      "id": "perri_s_leathers_57_7134",
      "name": "Perri's Leathers BM35PD-7134",
      "brand": "perri-s-leathers",
      "category": "general",
      "image_url": "/data/thumbnails/perri_s_leathers_57_7134.jpg",
      "description": "Perri's Leathers BM35PD-7134"
    },
    {
      "id": "perri_s_leathers_57_8172",
      "name": "Perri's Leathers UKNWSP-8172",
      "brand": "perri-s-leathers",
      "category": "general",
      "image_url": "/data/thumbnails/perri_s_leathers_57_8172.jpg",
      "description": "Perri's Leathers UKNWSP-8172"
    },
    {
      "id": "perri_s_leathers_57_7553",
      "name": "Perri's Leathers VGS-7553",
      "brand": "perri-s-leathers",
      "category": "general",
      "image_url": "/data/thumbnails/perri_s_leathers_57_7553.jpg",
      "description": "Perri's Leathers VGS-7553"
    },
    {
      "id": "perri_s_leathers_57_7135",
      "name": "Perri's Leathers BM35PD-7135",
      "brand": "perri-s-leathers",
      "category": "general",
      "image_url": "/data/thumbnails/perri_s_leathers_57_7135.jpg",
      "description": "Perri's Leathers BM35PD-7135"
    },
    {
      "id": "perri_s_leathers_57_6556",
      "name": "Perri's Leathers P25SSH-6556",
      "brand": "perri-s-leathers",
      "category": "general",
      "image_url": "/data/thumbnails/perri_s_leathers_57_6556.jpg",
      "description": "Perri's Leathers P25SSH-6556"
    },
    {
      "id": "perri_s_leathers_57_8265",
      "name": "Perri's Leathers P25EPV-8265",
      "brand": "perri-s-leathers",
      "category": "general",
      "image_url": "/data/thumbnails/perri_s_leathers_57_8265.jpg",
      "description": "Perri's Leathers P25EPV-8265"
    },
    {
      "id": "perri_s_leathers_57_7555",
      "name": "Perri's Leathers VGS-7555",
      "brand": "perri-s-leathers",
      "category": "general",
      "image_url": "/data/thumbnails/perri_s_leathers_57_7555.jpg",
      "description": "Perri's Leathers VGS-7555"
    },
    {
      "id": "perri_s_leathers_57_8092",
      "name": "Perri's Leathers LPCP-8092",
      "brand": "perri-s-leathers",
      "category": "general",
      "image_url": "/data/thumbnails/perri_s_leathers_57_8092.jpg",
      "description": "Perri's Leathers LPCP-8092"
    },
    {
      "id": "perri_s_leathers_57_1333",
      "name": "Perri's Leathers P25INM-1333",
      "brand": "perri-s-leathers",
      "category": "general",
      "image_url": "/data/thumbnails/perri_s_leathers_57_1333.jpg",
      "description": "Perri's Leathers P25INM-1333"
    }
  ]
}