{
  "brand_id": "nord",
  "brand_name": "Nord",
  "source": "v3.6_static_build",
  "build_timestamp": "2026-01-16T08:42:45.960859Z",
  "stats": {
    "total_products": 13,
    "verified_products": 0,
    "verification_rate": 0.0,
    "original_count": 13,
    "removed_duplicates": 0
  },
  "products": [
    {
      "name": "Nord Drum 3P",
      "image_url": "https://assets.nordkeyboards.com/nord-assets-prod/media/documents/N3P_logo_Xheight.svg",
      "detail_url": "https://www.nordkeyboards.com/products/nord-drum-3p",
      "brand": "Nord",
      "category": "Drums & Percussion",
      "brand_product_url": "https://www.nordkeyboards.com/products/nord-drum-3p",
      "verified": false,
      "verification_confidence": 0.0
    },
    {
      "name": "Nord Electro 6D 73",
      "image_url": "https://assets.nordkeyboards.com/nord-assets-prod/media/documents/NE6_logo_Xheight.svg",
      "detail_url": "https://www.nordkeyboards.com/products/nord-electro-6",
      "brand": "Nord",
      "category": "Synthesizers & Keys",
      "brand_product_url": "https://www.nordkeyboards.com/products/nord-electro-6",
      "verified": false,
      "verification_confidence": 0.0
    },
    {
      "name": "Nord Electro 6D 61",
      "image_url": "https://assets.nordkeyboards.com/nord-assets-prod/media/documents/NE6_logo_Xheight.svg",
      "detail_url": "https://www.nordkeyboards.com/products/nord-electro-6",
      "brand": "Nord",
      "category": "Synthesizers & Keys",
      "brand_product_url": "https://www.nordkeyboards.com/products/nord-electro-6",
      "verified": false,
      "verification_confidence": 0.0
    },
    {
      "name": "Nord Electro 6 HP",
      "image_url": "https://assets.nordkeyboards.com/nord-assets-prod/media/documents/NE6_logo_Xheight.svg",
      "detail_url": "https://www.nordkeyboards.com/products/nord-electro-6",
      "brand": "Nord",
      "category": "Synthesizers & Keys",
      "brand_product_url": "https://www.nordkeyboards.com/products/nord-electro-6",
      "verified": false,
      "verification_confidence": 0.0
    },
    {
      "name": "Nord Grand",
      "image_url": "https://assets.nordkeyboards.com/nord-assets-prod/media/documents/Nord_Grand_2_logo.svg",
      "detail_url": "https://www.nordkeyboards.com/products/nord-grand-2",
      "brand": "Nord",
      "category": "Grand",
      "brand_product_url": "https://www.nordkeyboards.com/products/nord-grand-2",
      "verified": false,
      "verification_confidence": 0.0
    },
    {
      "name": "Nord Lead A1",
      "image_url": "https://assets.nordkeyboards.com/nord-assets-prod/media/documents/NLA1_logo_Xheight.svg",
      "detail_url": "https://www.nordkeyboards.com/products/nord-lead-a1",
      "brand": "Nord",
      "category": "Lead",
      "brand_product_url": "https://www.nordkeyboards.com/products/nord-lead-a1",
      "verified": false,
      "verification_confidence": 0.0
    },
    {
      "name": "Nord Organ 3",
      "image_url": "https://assets.nordkeyboards.com/nord-assets-prod/media/documents/AgGiJQoE/Organ3%20logo%20beta.svg",
      "detail_url": "https://www.nordkeyboards.com/products/nord-organ-3",
      "brand": "Nord",
      "category": "Synthesizers & Keys",
      "brand_product_url": "https://www.nordkeyboards.com/products/nord-organ-3",
      "verified": false,
      "verification_confidence": 0.0
    },
    {
      "name": "Nord Piano 6 88",
      "image_url": "https://assets.nordkeyboards.com/nord-assets-prod/media/documents/DCBsGZq6/Nord%20Piano%206%20logo.svg",
      "detail_url": "https://www.nordkeyboards.com/products/nord-piano-6",
      "brand": "Nord",
      "category": "Synthesizers & Keys",
      "brand_product_url": "https://www.nordkeyboards.com/products/nord-piano-6",
      "verified": false,
      "verification_confidence": 0.0
    },
    {
      "name": "Nord Piano 6 73",
      "image_url": "https://assets.nordkeyboards.com/nord-assets-prod/media/documents/DCBsGZq6/Nord%20Piano%206%20logo.svg",
      "detail_url": "https://www.nordkeyboards.com/products/nord-piano-6",
      "brand": "Nord",
      "category": "Synthesizers & Keys",
      "brand_product_url": "https://www.nordkeyboards.com/products/nord-piano-6",
      "verified": false,
      "verification_confidence": 0.0
    },
    {
      "name": "Nord Stage 4 88",
      "image_url": "https://assets.nordkeyboards.com/nord-assets-prod/media/documents/Stage4_logo.svg",
      "detail_url": "https://www.nordkeyboards.com/products/nord-stage-4",
      "brand": "Nord",
      "category": "Synthesizers & Keys",
      "brand_product_url": "https://www.nordkeyboards.com/products/nord-stage-4",
      "verified": false,
      "verification_confidence": 0.0
    },
    {
      "name": "Nord Stage 4 73",
      "image_url": "https://assets.nordkeyboards.com/nord-assets-prod/media/documents/Stage4_logo.svg",
      "detail_url": "https://www.nordkeyboards.com/products/nord-stage-4",
      "brand": "Nord",
      "category": "Synthesizers & Keys",
      "brand_product_url": "https://www.nordkeyboards.com/products/nord-stage-4",
      "verified": false,
      "verification_confidence": 0.0
    },
    {
      "name": "Nord Stage 4 Compact",
      "image_url": "https://assets.nordkeyboards.com/nord-assets-prod/media/documents/Stage4_logo.svg",
      "detail_url": "https://www.nordkeyboards.com/products/nord-stage-4",
      "brand": "Nord",
      "category": "Synthesizers & Keys",
      "brand_product_url": "https://www.nordkeyboards.com/products/nord-stage-4",
      "verified": false,
      "verification_confidence": 0.0
    },
    {
      "name": "Nord Wave 2",
      "image_url": "https://assets.nordkeyboards.com/nord-assets-prod/media/documents/NW2_logo_Xheight.svg",
      "detail_url": "https://www.nordkeyboards.com/products/nord-wave-2",
      "brand": "Nord",
      "category": "Wave",
      "brand_product_url": "https://www.nordkeyboards.com/products/nord-wave-2",
      "verified": false,
      "verification_confidence": 0.0
    }
  ]
}