{
  "id": "allen_heath_40_xone922",
  "name": "Allen & Heath Xone:92 MK2",
  "brand": "allen-heath",
  "category": "live",
  "description": "Allen & Heath Xone:92 MK2",
  "media": {
    "thumbnail": "https://d3m9l0v76dty0.cloudfront.net/system/photos/15523896/original/825d03580a2851e4010cc1cd695f5afe.jpg",
    "gallery": [],
    "videos": []
  },
  "commercial": {
    "price": 8158.0,
    "link": "https://www.halilit.com/items/7446144-allen-heath-xone-92-mk2",
    "status": "IN_STOCK"
  },
  "specs": {},
  "badges": [
    "HALILIT_CERTIFIED"
  ],
  "meta": {
    "completeness": "SKELETON",
    "last_scan": "2026-01-24T04:09:51.172921Z"
  }
}