{
  "id": "rcf_61_nx915a",
  "name": "RCF NX 915-A",
  "brand": "rcf",
  "category": "general",
  "description": "RCF NX 915-A",
  "media": {
    "thumbnail": "https://d3m9l0v76dty0.cloudfront.net/system/photos/12830235/original/ef557947a84527303790bd4bc10e5725.jpg",
    "gallery": [],
    "videos": []
  },
  "commercial": {
    "price": 6545.0,
    "link": "https://www.halilit.com/items/6130179-rcf-nx-915-a-professional-active-speaker-",
    "status": "IN_STOCK"
  },
  "specs": {},
  "badges": [
    "HALILIT_CERTIFIED"
  ],
  "meta": {
    "completeness": "SKELETON",
    "last_scan": "2026-01-24T04:09:15.875053Z"
  }
}