{
  "id": "rcf_61_sub9007as_cover",
  "name": "RCF SUB 9007-AS Protection Cover",
  "brand": "rcf",
  "category": "accessories",
  "description": "RCF SUB 9007-AS Protection Cover",
  "media": {
    "thumbnail": "https://d3m9l0v76dty0.cloudfront.net/system/photos/2071402/original/d506f96463528358c782a0fd46f2ea0f.jpg",
    "gallery": [],
    "videos": []
  },
  "commercial": {
    "price": 665.0,
    "link": "https://www.halilit.com/items/1354826-rcf-sub-9007-as-protection-cover",
    "status": "IN_STOCK"
  },
  "specs": {},
  "badges": [
    "HALILIT_CERTIFIED"
  ],
  "meta": {
    "completeness": "SKELETON",
    "last_scan": "2026-01-24T04:09:15.879553Z"
  }
}