{
  "brand_id": "headrush-fx",
  "halilit_count": 14,
  "brand_website_count": 0,
  "common_count": 0,
  "gap_count": 0,
  "halilit_only_count": 14,
  "coverage_percentage": 0,
  "gap_products": [],
  "common_products": [],
  "halilit_exclusive": [
    {
      "halilit_id": "3319934",
      "item_code": "52-FRFR112",
      "category": "מגברי חשמליות",
      "name": "מוניטור מוגבר לגיטרה ובס Headrush FRFR-112",
      "url": "https://www.halilit.com  /items/3319934-headrush-frfr-112\n",
      "image_url": "https://d3m9l0v76dty0.cloudfront.net/system/photos/5777953/original/c5089e9581dc9179df808b3ddee8091f.jpg",
      "thumbnail_url": "https://d3m9l0v76dty0.cloudfront.net/system/photos/5777953/original/c5089e9581dc9179df808b3ddee8091f.jpg",
      "price": "1728",
      "currency": "ILS",
      "brand": "headrush-fx",
      "source": "halilit",
      "distributor": "Halilit Music Center"
    },
    {
      "halilit_id": "7456924",
      "item_code": "52-SHEERANLOOPERX",
      "category": "פדלים ומולטי אפקט ",
      "name": "HeadRush Sheeran Looper X",
      "url": "https://www.halilit.com  /items/7456924-headrush-sheeran-looper-x\n",
      "image_url": "https://d3m9l0v76dty0.cloudfront.net/system/photos/15549629/original/1be9fdd697b0ce0a77d05f646d2e4ec4.jpg",
      "thumbnail_url": "https://d3m9l0v76dty0.cloudfront.net/system/photos/15549629/original/1be9fdd697b0ce0a77d05f646d2e4ec4.jpg",
      "price": "6096",
      "currency": "ILS",
      "brand": "headrush-fx",
      "source": "halilit",
      "distributor": "Halilit Music Center"
    },
    {
      "halilit_id": "6644810",
      "item_code": "52-SHEERANLOOPER+",
      "category": "פדלים ומולטי אפקט ",
      "name": "+ HeadRush Sheeran Looper",
      "url": "https://www.halilit.com  /items/6644810--headrush-sheeran-looper\n",
      "image_url": "https://d3m9l0v76dty0.cloudfront.net/system/photos/13968222/original/71cb4631e6cc2935f97287d615b2e318.jpg",
      "thumbnail_url": "https://d3m9l0v76dty0.cloudfront.net/system/photos/13968222/original/71cb4631e6cc2935f97287d615b2e318.jpg",
      "price": "1416",
      "currency": "ILS",
      "brand": "headrush-fx",
      "source": "halilit",
      "distributor": "Halilit Music Center"
    },
    {
      "halilit_id": "2495029",
      "item_code": "52-LOOPERBOARD",
      "category": "פדלים ומולטי אפקט ",
      "name": "HeadRush Looperboard",
      "url": "https://www.halilit.com  /items/2495029-headrush-looperboard\n",
      "image_url": "https://d3m9l0v76dty0.cloudfront.net/system/photos/4125492/original/70c96cacd9b239c1b9323f70d7234fb1.jpg",
      "thumbnail_url": "https://d3m9l0v76dty0.cloudfront.net/system/photos/4125492/original/70c96cacd9b239c1b9323f70d7234fb1.jpg",
      "price": "4390",
      "currency": "ILS",
      "brand": "headrush-fx",
      "source": "halilit",
      "distributor": "Halilit Music Center"
    },
    {
      "halilit_id": "6000997",
      "item_code": "52-HRPRIME",
      "category": "פדלים ומולטי אפקט ",
      "name": "מולטי אפקט HeadRush Prime",
      "url": "https://www.halilit.com  /items/6000997-headrush-prime-\n",
      "image_url": "https://d3m9l0v76dty0.cloudfront.net/system/photos/12527722/original/ac985786c87996a0101bbd774341deb8.jpg",
      "thumbnail_url": "https://d3m9l0v76dty0.cloudfront.net/system/photos/12527722/original/ac985786c87996a0101bbd774341deb8.jpg",
      "price": "4952",
      "currency": "ILS",
      "brand": "headrush-fx",
      "source": "halilit",
      "distributor": "Halilit Music Center"
    },
    {
      "halilit_id": "1517026",
      "item_code": "52-HDRSH-PDB",
      "category": "פדלים ומולטי אפקט ",
      "name": "מולטי אפקט HeadRush Pedalboard",
      "url": "https://www.halilit.com  /items/1517026-headrush-pedalboard\n",
      "image_url": "https://d3m9l0v76dty0.cloudfront.net/system/photos/2391104/original/f3ef9f1ea1521031c720c109fa1c746e.jpg",
      "thumbnail_url": "https://d3m9l0v76dty0.cloudfront.net/system/photos/2391104/original/f3ef9f1ea1521031c720c109fa1c746e.jpg",
      "price": "4538",
      "currency": "ILS",
      "brand": "headrush-fx",
      "source": "halilit",
      "distributor": "Halilit Music Center"
    },
    {
      "halilit_id": "3180636",
      "item_code": "52-HREXPRESSION",
      "category": "פדלים ומולטי אפקט ",
      "name": "HeadRush Expression Pedal",
      "url": "https://www.halilit.com  /items/3180636-headrush-expression-pedal\n",
      "image_url": "https://d3m9l0v76dty0.cloudfront.net/system/photos/5474850/original/97e806ec29eedcdfc73e4df8d1e0d1df.jpg",
      "thumbnail_url": "https://d3m9l0v76dty0.cloudfront.net/system/photos/5474850/original/97e806ec29eedcdfc73e4df8d1e0d1df.jpg",
      "price": "684",
      "currency": "ILS",
      "brand": "headrush-fx",
      "source": "halilit",
      "distributor": "Halilit Music Center"
    },
    {
      "halilit_id": "7940880",
      "item_code": "52-FLEX",
      "category": "פדלים ומולטי אפקט ",
      "name": "מולטי אפקט HeadRush Flex Prime",
      "url": "https://www.halilit.com  /items/7940880-headrush-flex-prime-multi-effect-pedal\n",
      "image_url": "https://d3m9l0v76dty0.cloudfront.net/system/photos/16596944/original/a1bc63693f1099244af8d6ac988a407f.jpg",
      "thumbnail_url": "https://d3m9l0v76dty0.cloudfront.net/system/photos/16596944/original/a1bc63693f1099244af8d6ac988a407f.jpg",
      "price": "2695",
      "currency": "ILS",
      "brand": "headrush-fx",
      "source": "halilit",
      "distributor": "Halilit Music Center"
    },
    {
      "halilit_id": "3180573",
      "item_code": "52-FRFR108",
      "category": "מגברי חשמליות",
      "name": "מוניטור מוגבר לגיטרה ובס Headrush FRFR-108",
      "url": "https://www.halilit.com  /items/3180573-headrush-frfr-108\n",
      "image_url": "https://d3m9l0v76dty0.cloudfront.net/system/photos/5474735/original/d1c272d948104aafa530511ec0ebb5fe.jpg",
      "thumbnail_url": "https://d3m9l0v76dty0.cloudfront.net/system/photos/5474735/original/d1c272d948104aafa530511ec0ebb5fe.jpg",
      "price": "1325",
      "currency": "ILS",
      "brand": "headrush-fx",
      "source": "halilit",
      "distributor": "Halilit Music Center"
    },
    {
      "halilit_id": "4147422",
      "item_code": "52-MX5",
      "category": "פדלים ומולטי אפקט ",
      "name": "מולטי אפקט HeadRush MX5",
      "url": "https://www.halilit.com  /items/4147422-headrush-mx5-the-most-powerful-compact-guitar-fx-and-amp-modeling-processor-\n",
      "image_url": "https://d3m9l0v76dty0.cloudfront.net/system/photos/7561375/original/40461278a94e4cb04938fc72645f7519.jpg",
      "thumbnail_url": "https://d3m9l0v76dty0.cloudfront.net/system/photos/7561375/original/40461278a94e4cb04938fc72645f7519.jpg",
      "price": "2300",
      "currency": "ILS",
      "brand": "headrush-fx",
      "source": "halilit",
      "distributor": "Halilit Music Center"
    },
    {
      "halilit_id": "8524721",
      "item_code": "52-FRFR108MK2",
      "category": "מגברי חשמליות",
      "name": "קבינה לגיטרה ובס Headrush FRFR-108 MKII",
      "url": "https://www.halilit.com  /items/8524721-headrush-frfr-108-mkii-guitar-cabinet\n",
      "image_url": "https://d3m9l0v76dty0.cloudfront.net/system/photos/18472392/original/aaae80228c0bbac35236941e7ab1cd71.jpg",
      "thumbnail_url": "https://d3m9l0v76dty0.cloudfront.net/system/photos/18472392/original/aaae80228c0bbac35236941e7ab1cd71.jpg",
      "price": "1603",
      "currency": "ILS",
      "brand": "headrush-fx",
      "source": "halilit",
      "distributor": "Halilit Music Center"
    },
    {
      "halilit_id": "8183198",
      "item_code": "52-AUTOTUNE",
      "category": "פדלים ומולטי אפקט ",
      "name": "פדל HeadRush VX5 Vocal Effects",
      "url": "https://www.halilit.com  /items/8183198-headrush-vx5-vocal-effects-pedal\n",
      "image_url": "https://d3m9l0v76dty0.cloudfront.net/system/photos/17138125/original/e0b3aa6ede14d495822dff1f24994dc0.jpg",
      "thumbnail_url": "https://d3m9l0v76dty0.cloudfront.net/system/photos/17138125/original/e0b3aa6ede14d495822dff1f24994dc0.jpg",
      "price": "1329",
      "currency": "ILS",
      "brand": "headrush-fx",
      "source": "halilit",
      "distributor": "Halilit Music Center"
    },
    {
      "halilit_id": "7253063",
      "item_code": "52-FRFR112MK2",
      "category": "מגברי חשמליות",
      "name": "מוניטור מוגבר לגיטרה/בס Headrush FRFR-112 MK2",
      "url": "https://www.halilit.com  /items/7253063-headrush-frfr-112-mk2\n",
      "image_url": "https://d3m9l0v76dty0.cloudfront.net/system/photos/15112272/original/2459b77a90f0088084121c5c6efd2447.jpg",
      "thumbnail_url": "https://d3m9l0v76dty0.cloudfront.net/system/photos/15112272/original/2459b77a90f0088084121c5c6efd2447.jpg",
      "price": "1806",
      "currency": "ILS",
      "brand": "headrush-fx",
      "source": "halilit",
      "distributor": "Halilit Music Center"
    },
    {
      "halilit_id": "6554516",
      "item_code": "52-HRCOREXEUK",
      "category": "פדלים ומולטי אפקט ",
      "name": "מולטי אפקט HeadRush Core",
      "url": "https://www.halilit.com  /items/6554516-headrush-core\n",
      "image_url": "https://d3m9l0v76dty0.cloudfront.net/system/photos/13773773/original/d934f4cc1125af8857190cc3b6b50ac2.jpg",
      "thumbnail_url": "https://d3m9l0v76dty0.cloudfront.net/system/photos/13773773/original/d934f4cc1125af8857190cc3b6b50ac2.jpg",
      "price": "3713",
      "currency": "ILS",
      "brand": "headrush-fx",
      "source": "halilit",
      "distributor": "Halilit Music Center"
    }
  ]
}